environeer/__init__.py
environeer/cli.py
environeer/config.py
environeer/base/__init__.py
environeer/base/node.py
environeer/base/root.py
environeer/core/__init__.py
environeer/core/controller.py
environeer/core/dataset.py
environeer/core/diffuser.py
environeer/core/space.py
environeer/core/transformer.py
environeer-0.1.0a0.dist-info/LICENSE
environeer-0.1.0a0.dist-info/METADATA
environeer-0.1.0a0.dist-info/WHEEL
environeer-0.1.0a0.dist-info/entry_points.txt
environeer-0.1.0a0.dist-info/top_level.txt
environeer-0.1.0a0.dist-info/RECORD
