Metadata-Version: 2.1
Name: environeer
Version: 0.1.0a0
Author: 
Author-email: 
License: Apache 2.0
Classifier: Topic :: Scientific/Engineering :: Artificial Intelligence
Classifier: Topic :: Scientific/Engineering :: Information Analysis
Classifier: Operating System :: OS Independent
Classifier: Programming Language :: Python :: 3.8
Classifier: Programming Language :: Python :: 3.9
Classifier: Programming Language :: Python :: 3.10
Classifier: Programming Language :: Python :: 3.11
License-File: LICENSE
Requires-Dist: huggingface-hub
Requires-Dist: transformers
Requires-Dist: tokenizers
Requires-Dist: datasets
Requires-Dist: safetensors
Requires-Dist: gradio
Requires-Dist: typer
Requires-Dist: rich
Requires-Dist: python-dotenv
Provides-Extra: dev
Requires-Dist: ruff ; extra == 'dev'
Requires-Dist: black ; extra == 'dev'
Requires-Dist: pytest ; extra == 'dev'
Requires-Dist: mypy ; extra == 'dev'
Requires-Dist: bandit ; extra == 'dev'
Requires-Dist: coverage ; extra == 'dev'
Requires-Dist: pre-commit ; extra == 'dev'
Requires-Dist: isort ; extra == 'dev'
Provides-Extra: docs
Requires-Dist: mkdocstrings[python] ; extra == 'docs'
